pybline/__init__.py
pybline/gui.py
pybline/models.py
pybline/tools.py
pybline-0.1.0.dist-info/LICENSE
pybline-0.1.0.dist-info/METADATA
pybline-0.1.0.dist-info/WHEEL
pybline-0.1.0.dist-info/entry_points.txt
pybline-0.1.0.dist-info/top_level.txt
pybline-0.1.0.dist-info/RECORD
