Metadata-Version: 2.1
Name: pybline
Version: 0.1.0
Summary: Python baseline correction.
Home-page: http://github.com/arkottke/pybline
Author: Albert Kottke
Author-email: albert.kottke@gmail.com
License: MIT
Platform: UNKNOWN
Classifier: License :: OSI Approved :: MIT License
Classifier: Environment :: Console
Classifier: Natural Language :: English
Classifier: Operating System :: OS Independent
Classifier: Programming Language :: Python :: 3.6
Classifier: Programming Language :: Python
Classifier: Topic :: Scientific/Engineering
Classifier: Intended Audience :: Science/Research
Requires-Dist: numpy
Requires-Dist: numba
Requires-Dist: pyrotd
Requires-Dist: setuptools
